lddl/__init__.py
lddl/random.py
lddl/types.py
lddl/utils.py
lddl/dask/__init__.py
lddl/dask/load_balance.py
lddl/dask/readers.py
lddl/dask/bart/__init__.py
lddl/dask/bart/pretrain.py
lddl/dask/bert/__init__.py
lddl/dask/bert/binning.py
lddl/dask/bert/pretrain.py
lddl/download/__init__.py
lddl/download/books.py
lddl/download/common_crawl.py
lddl/download/openwebtext.py
lddl/download/utils.py
lddl/download/wikipedia.py
lddl/paddle/__init__.py
lddl/paddle/bert.py
lddl/paddle/dataloader.py
lddl/paddle/datasets.py
lddl/paddle/log.py
lddl/paddle/utils.py
lddl/torch/__init__.py
lddl/torch/bert.py
lddl/torch/dataloader.py
lddl/torch/datasets.py
lddl/torch/log.py
lddl/torch/utils.py
lddl/torch_mp/__init__.py
lddl/torch_mp/bert.py
lddl/torch_mp/dataloader.py
lddl/torch_mp/datasets.py
lddl/torch_mp/log.py
lddl/torch_mp/utils.py
lddl-0.1.0.dist-info/LICENSE
lddl-0.1.0.dist-info/METADATA
lddl-0.1.0.dist-info/WHEEL
lddl-0.1.0.dist-info/entry_points.txt
lddl-0.1.0.dist-info/top_level.txt
lddl-0.1.0.dist-info/RECORD
