Metadata-Version: 2.1
Name: lddl
Version: 0.1.0
Summary: Language Datasets and Data Loaders for NVIDIA Deep Learning Examples
Home-page: https://github.com/NVIDIA/lddl
Author: Shang Wang, Joseph Jennings, Bobby Chen, Shijie Wang, Peter Dykas
Author-email: jjennings@nvidia.com
Classifier: Development Status :: 3 - Alpha
Classifier: Programming Language :: Python :: 3 :: Only
Requires-Python: >=3.6
License-File: LICENSE
Requires-Dist: dask[complete] (==2021.7.1)
Requires-Dist: distributed (==2021.7.1)
Requires-Dist: dask-mpi (==2021.11.0)
Requires-Dist: bokeh (==2.4.3)
Requires-Dist: pyarrow (>=4.0.1)
Requires-Dist: mpi4py (==3.1.3)
Requires-Dist: transformers (==4.16.2)
Requires-Dist: wikiextractor (==3.0.6)
Requires-Dist: cchardet (==2.1.7)
Requires-Dist: awscli (>=1.22.55)
Requires-Dist: gdown (==4.5.3)
